k33kz/__init__.py
k33kz-1.0.1.dist-info/METADATA
k33kz-1.0.1.dist-info/WHEEL
k33kz-1.0.1.dist-info/top_level.txt
k33kz-1.0.1.dist-info/RECORD
