Metadata-Version: 2.4
Name: k33kz
Version: 1.0.1
Summary: Facebook Authentication Library with multiple login methods
Home-page: 
Author: Odai
Author-email: odaiobeidat00@gmail.com
Keywords: facebook,login,authentication,api,social
Classifier: Programming Language :: Python :: 3
Classifier: License :: OSI Approved :: MIT License
Classifier: Operating System :: OS Independent
Classifier: Development Status :: 4 - Beta
Classifier: Intended Audience :: Developers
Classifier: Topic :: Software Development :: Libraries :: Python Modules
Requires-Python: >=3.6
Requires-Dist: requests>=2.25.1
Dynamic: author
Dynamic: author-email
Dynamic: classifier
Dynamic: description
Dynamic: description-content-type
Dynamic: keywords
Dynamic: requires-dist
Dynamic: requires-python
Dynamic: summary
